cobweb/__init__.py
cobweb/constant.py
cobweb/setting.py
cobweb/base/__init__.py
cobweb/base/common_queue.py
cobweb/base/item.py
cobweb/base/logger.py
cobweb/base/request.py
cobweb/base/response.py
cobweb/base/seed.py
cobweb/base/task_queue.py
cobweb/base/test.py
cobweb/crawlers/__init__.py
cobweb/crawlers/crawler.py
cobweb/db/__init__.py
cobweb/db/api_db.py
cobweb/db/redis_db.py
cobweb/exceptions/__init__.py
cobweb/exceptions/oss_db_exception.py
cobweb/launchers/__init__.py
cobweb/launchers/distributor.py
cobweb/launchers/launcher.py
cobweb/launchers/uploader.py
cobweb/log_dots/__init__.py
cobweb/log_dots/dot.py
cobweb/log_dots/loghub_dot.py
cobweb/pipelines/__init__.py
cobweb/pipelines/pipeline.py
cobweb/pipelines/pipeline_csv.py
cobweb/pipelines/pipeline_loghub.py
cobweb/schedulers/__init__.py
cobweb/schedulers/scheduler.py
cobweb/schedulers/scheduler_with_redis.py
cobweb/utils/__init__.py
cobweb/utils/bloom.py
cobweb/utils/decorators.py
cobweb/utils/dotting.py
cobweb/utils/oss.py
cobweb/utils/tools.py
cobweb_launcher-3.2.28.dist-info/LICENSE
cobweb_launcher-3.2.28.dist-info/METADATA
cobweb_launcher-3.2.28.dist-info/WHEEL
cobweb_launcher-3.2.28.dist-info/top_level.txt
cobweb_launcher-3.2.28.dist-info/RECORD
