Metadata-Version: 2.1
Name: cobweb-launcher
Version: 3.2.28
Summary: spider_hole
Home-page: https://github.com/Juannie-PP/cobweb
Author: Juannie-PP
Author-email: 2604868278@qq.com
License: MIT
Keywords: cobweb-launcher,cobweb,spider
Platform: UNKNOWN
Classifier: Programming Language :: Python :: 3
Classifier: License :: OSI Approved :: MIT License
Classifier: Operating System :: OS Independent
Requires-Python: >=3.7
Requires-Dist: requests>=2.19.1
Requires-Dist: redis>=4.4.4
Requires-Dist: aliyun-log-python-sdk
